djangocms_slider_easy_uploadcare-0.3.9.dist-info/DESCRIPTION.rst
djangocms_slider_easy_uploadcare-0.3.9.dist-info/METADATA
djangocms_slider_easy_uploadcare-0.3.9.dist-info/RECORD
djangocms_slider_easy_uploadcare-0.3.9.dist-info/WHEEL
djangocms_slider_easy_uploadcare-0.3.9.dist-info/metadata.json
djangocms_slider_easy_uploadcare-0.3.9.dist-info/top_level.txt
djangocms_slider_uploadcare/__init__.py
djangocms_slider_uploadcare/cms_plugins.py
djangocms_slider_uploadcare/models.py
djangocms_slider_uploadcare/locale/en/LC_MESSAGES/django.mo
djangocms_slider_uploadcare/locale/en/LC_MESSAGES/django.po
djangocms_slider_uploadcare/locale/nl/LC_MESSAGES/django.mo
djangocms_slider_uploadcare/locale/nl/LC_MESSAGES/django.po
djangocms_slider_uploadcare/migrations/0001_initial.py
djangocms_slider_uploadcare/migrations/__init__.py
djangocms_slider_uploadcare/templates/djangocms_slider_uploadcare/slide.html
djangocms_slider_uploadcare/templates/djangocms_slider_uploadcare/slider.html
