Metadata-Version: 2.0
Name: djangocms-slider-easy-uploadcare
Version: 0.3.9
Summary: A slider plugin for djangocms that lets you arrange slides like any other djangocms plugin. Fork of urga/djangocms-slider, but using uploadcare.
Home-page: https://github.com/Zowie/djangocms-slider-easy-uploadcare
Author: Luminum Solutions
Author-email: zowie@akoten.com
License: BSD
Keywords: slideshow,django,cms,plugin,uploadcare,flexslider,jquery
Platform: UNKNOWN
Classifier: Development Status :: 3 - Alpha
Classifier: Framework :: Django
Classifier: Framework :: Django :: 1.8
Classifier: Intended Audience :: Developers
Classifier: License :: OSI Approved :: BSD License
Classifier: Natural Language :: English
Classifier: Natural Language :: Dutch
Classifier: Programming Language :: Python :: 2
Classifier: Programming Language :: Python :: 2.7
Classifier: Programming Language :: Python :: 3
Classifier: Programming Language :: Python :: 3.3
Classifier: Programming Language :: Python :: 3.4
Classifier: Programming Language :: Python :: 3.5
Classifier: Programming Language :: Python :: 3.6
Requires-Dist: django (>=1.8.0,<1.11)
Requires-Dist: django-cms (>=3.0)
Requires-Dist: pyuploadcare (==2.2.1)
